llama_index/retrievers/relik/__init__.py
llama_index/retrievers/relik/base.py
llama_index_retrievers_relik-0.1.0.dist-info/METADATA
llama_index_retrievers_relik-0.1.0.dist-info/WHEEL
llama_index_retrievers_relik-0.1.0.dist-info/RECORD
