Metadata-Version: 2.1
Name: llama-index-retrievers-relik
Version: 0.1.0
Summary: llama-index retrievers relik integration
License: MIT
Author: Your Name
Author-email: you@example.com
Requires-Python: >=3.10,<4.0
Classifier: License :: OSI Approved :: MIT License
Classifier: Programming Language :: Python :: 3
Classifier: Programming Language :: Python :: 3.10
Classifier: Programming Language :: Python :: 3.11
Classifier: Programming Language :: Python :: 3.12
Requires-Dist: huggingface-hub (<0.24.0)
Requires-Dist: llama-index-core (>=0.10.1,<0.11.0)
Requires-Dist: relik (>=1.0.3,<2.0.0)
